CHANGES.txt
README.txt
pypi_upload.sh
setup.cfg
setup.py
collective/__init__.py
collective.fancyzoomview.egg-info/PKG-INFO
collective.fancyzoomview.egg-info/SOURCES.txt
collective.fancyzoomview.egg-info/dependency_links.txt
collective.fancyzoomview.egg-info/entry_points.txt
collective.fancyzoomview.egg-info/namespace_packages.txt
collective.fancyzoomview.egg-info/not-zip-safe
collective.fancyzoomview.egg-info/requires.txt
collective.fancyzoomview.egg-info/top_level.txt
collective/fancyzoomview/README.txt
collective/fancyzoomview/__init__.py
collective/fancyzoomview/configure.zcml
collective/fancyzoomview/overrides.zcml
collective/fancyzoomview/setuphandlers.py
collective/fancyzoomview/version.txt
collective/fancyzoomview/browser/__init__.py
collective/fancyzoomview/browser/configure.zcml
collective/fancyzoomview/browser/fancyzoomview.pt
collective/fancyzoomview/browser/newsitem_view.pt
collective/fancyzoomview/browser/views.py
collective/fancyzoomview/browser/images/bl.gif
collective/fancyzoomview/browser/images/bl.png
collective/fancyzoomview/browser/images/bm.gif
collective/fancyzoomview/browser/images/bm.png
collective/fancyzoomview/browser/images/br.gif
collective/fancyzoomview/browser/images/br.png
collective/fancyzoomview/browser/images/closebox.gif
collective/fancyzoomview/browser/images/closebox.png
collective/fancyzoomview/browser/images/ml.gif
collective/fancyzoomview/browser/images/ml.png
collective/fancyzoomview/browser/images/mr.gif
collective/fancyzoomview/browser/images/mr.png
collective/fancyzoomview/browser/images/tl.gif
collective/fancyzoomview/browser/images/tl.png
collective/fancyzoomview/browser/images/tm.gif
collective/fancyzoomview/browser/images/tm.png
collective/fancyzoomview/browser/images/tr.gif
collective/fancyzoomview/browser/images/tr.png
collective/fancyzoomview/browser/javascript/fancyzoom.js
collective/fancyzoomview/browser/javascript/fancyzoom.min.js
collective/fancyzoomview/profiles/default/collective.fancyzoomview_various.txt
collective/fancyzoomview/profiles/default/import_steps.xml
collective/fancyzoomview/profiles/default/metadata.xml
collective/fancyzoomview/tests/__init__.py
collective/fancyzoomview/tests/base.py
collective/fancyzoomview/tests/test_doctest.py
docs/INSTALL.txt
docs/LICENSE.GPL
docs/LICENSE.txt