Metadata-Version: 1.0
Name: collective.fancyzoomview
Version: 1.0.2
Summary: Smooth javascript image zooming for Plone folders and topics.
Home-page: http://pypi.python.org/pypi/collective.fancyzoomview
Author: Timo Stollenwerk
Author-email: timo@zmag.de
License: GPL
Keywords: plone javascript image
Platform: UNKNOWN
Classifier: Framework :: Plone
Classifier: Programming Language :: Python
Classifier: Topic :: Software Development :: Libraries :: Python Modules
